walk/__init__.py
walk/argsextractor.py
walk/connector.py
walk/cursor.py
walk/utils.py
walk/walk.py
walk-0.3.5.dist-info/LICENSE
walk-0.3.5.dist-info/METADATA
walk-0.3.5.dist-info/WHEEL
walk-0.3.5.dist-info/entry_points.txt
walk-0.3.5.dist-info/top_level.txt
walk-0.3.5.dist-info/RECORD
