Metadata-Version: 2.1
Name: walk
Version: 0.3.5
Summary: PostgreSQL and MySQL. Database migration and seeds tool for postgres and mysql by using psycopg2 and mysql-connector with python3.
Home-page: https://github.com/willybaer/walk
Author: Wilhelm Dewald
License: UNKNOWN
Platform: UNKNOWN
Classifier: Programming Language :: Python :: 3
Classifier: License :: OSI Approved :: MIT License
Classifier: Operating System :: OS Independent
Requires-Python: >3.5.9
